psgui_util/__init__.py
psgui_util-0.1.dist-info/LICENSE.txt
psgui_util-0.1.dist-info/METADATA
psgui_util-0.1.dist-info/WHEEL
psgui_util-0.1.dist-info/top_level.txt
psgui_util-0.1.dist-info/RECORD
